torch_incremental_pca/__init__.py
torch_incremental_pca/incremental_pca.py
torch_incremental_pca-0.0.14.dist-info/METADATA
torch_incremental_pca-0.0.14.dist-info/WHEEL
torch_incremental_pca-0.0.14.dist-info/top_level.txt
torch_incremental_pca-0.0.14.dist-info/RECORD
