Metadata-Version: 2.1
Name: torch-incremental-pca
Version: 0.0.14
Summary: A PyTorch implementation of Incremental PCA
Author-email: Lukas Hauzenberger <lukas.hauzenberger@gmail.com>
Classifier: Programming Language :: Python :: 3
Classifier: License :: OSI Approved :: MIT License
Classifier: Operating System :: OS Independent
Requires-Python: >=3.8
Requires-Dist: torch
Requires-Dist: numpy
